submagic_mcp/__init__.py
submagic_mcp_server-1.1.0.dist-info/licenses/LICENSE
submagic_mcp_server-1.1.0.dist-info/METADATA
submagic_mcp_server-1.1.0.dist-info/WHEEL
submagic_mcp_server-1.1.0.dist-info/entry_points.txt
submagic_mcp_server-1.1.0.dist-info/top_level.txt
submagic_mcp_server-1.1.0.dist-info/RECORD
