Metadata-Version: 2.4
Name: submagic-mcp-server
Version: 1.1.0
Summary: AI-powered video editing MCP server with Submagic API integration
Author-email: Sid Dani <sidart10@github.com>
License: MIT
Project-URL: Homepage, https://github.com/sidart10/submagic-mcp-server
Project-URL: Documentation, https://github.com/sidart10/submagic-mcp-server#readme
Project-URL: Repository, https://github.com/sidart10/submagic-mcp-server
Project-URL: Issues, https://github.com/sidart10/submagic-mcp-server/issues
Keywords: mcp,model-context-protocol,video-editing,ai,submagic,captions,automation
Classifier: Development Status :: 5 - Production/Stable
Classifier: Intended Audience :: Developers
Classifier: Topic :: Software Development :: Libraries :: Python Modules
Classifier: Topic :: Multimedia :: Video
Classifier: License :: OSI Approved :: MIT License
Classifier: Programming Language :: Python :: 3
Classifier: Programming Language :: Python :: 3.8
Classifier: Programming Language :: Python :: 3.9
Classifier: Programming Language :: Python :: 3.10
Classifier: Programming Language :: Python :: 3.11
Classifier: Programming Language :: Python :: 3.12
Classifier: Operating System :: OS Independent
Requires-Python: >=3.8
License-File: LICENSE
Requires-Dist: mcp>=1.0.0
Requires-Dist: httpx>=0.27.0
Requires-Dist: pydantic>=2.0.0
Requires-Dist: python-dotenv>=1.0.0
Dynamic: license-file
